{"version":1,"resource":"file:///home/michail/work/Quanti/magento-tests/cypress/support/magento/filter_cutomers.ts","entries":[{"id":"CM4K.ts","timestamp":1652362368663},{"id":"PyuD.ts","timestamp":1652362594017},{"id":"kHZF.ts","timestamp":1652362645577},{"id":"fO6f.ts","timestamp":1652362697997},{"id":"kr9n.ts","timestamp":1652362742974},{"id":"hqEn.ts","timestamp":1652362756740},{"id":"2vJb.ts","timestamp":1652362922931},{"id":"9Vuw.ts","timestamp":1652363027928},{"id":"rEsH.ts","timestamp":1652363079272},{"id":"DQjX.ts","timestamp":1652363203452},{"id":"mP3x.ts","timestamp":1652363358637},{"id":"ukJK.ts","timestamp":1652363395570},{"id":"pKgo.ts","timestamp":1652363430310},{"id":"Y2he.ts","timestamp":1652363458884},{"id":"y0XX.ts","timestamp":1652363629178}]}