{"version":1,"resource":"file:///home/michail/work/Quanti/magento-tests/cypress/integration/reviews/guest_review.spec.ts","entries":[{"id":"iP84.ts","timestamp":1652444527421},{"id":"ephh.ts","timestamp":1652444626433},{"id":"XHSr.ts","timestamp":1652444676102},{"id":"px3l.ts","timestamp":1652444718242},{"id":"PnAv.ts","timestamp":1652444795308},{"id":"CnKI.ts","timestamp":1652444861609},{"id":"hR9c.ts","timestamp":1652444911501},{"id":"wDuJ.ts","timestamp":1652445225345},{"id":"JfC9.ts","timestamp":1652445247935},{"id":"cBqH.ts","timestamp":1652445337334},{"id":"y6O6.ts","timestamp":1652445406555},{"id":"GJxe.ts","timestamp":1652445524358},{"id":"IG1e.ts","timestamp":1652445575394},{"id":"msOi.ts","timestamp":1652445643502},{"id":"54Vm.ts","timestamp":1652781091877},{"id":"uZGg.ts","timestamp":1652968625257},{"id":"daxG.ts","timestamp":1652970452088},{"id":"CM6E.ts","timestamp":1652970609593},{"id":"OWtM.ts","timestamp":1652970778192},{"id":"xv27.ts","timestamp":1652970955819},{"id":"bLH2.ts","timestamp":1652972287668},{"id":"CM15.ts","timestamp":1652972363812},{"id":"scev.ts","timestamp":1652972479031},{"id":"ZNby.ts","timestamp":1652972509219},{"id":"UVsE.ts","timestamp":1652973192546},{"id":"GT09.ts","timestamp":1652973251935},{"id":"weys.ts","timestamp":1652973299775},{"id":"O32W.ts","timestamp":1652977839796},{"id":"Z4Go.ts","timestamp":1653041559240},{"id":"0kV4.ts","timestamp":1653041697747},{"id":"mSCq.ts","timestamp":1653041728304},{"id":"ovq8.ts","timestamp":1653041783668},{"id":"YQ8f.ts","timestamp":1653041896408},{"id":"OWkT.ts","timestamp":1653042116379},{"id":"iMTo.ts","timestamp":1653042171939},{"id":"GtuR.ts","timestamp":1653042224893},{"id":"qG9t.ts","timestamp":1653042263483},{"id":"k7JB.ts","timestamp":1653042364710},{"id":"8M2A.ts","timestamp":1653045004880},{"id":"3Pns.ts","timestamp":1653050842663},{"id":"fGlc.ts","timestamp":1653307809469},{"id":"ID82.ts","timestamp":1653307828386},{"id":"ICQ1.ts","source":"Workspace Edit","timestamp":1653308721712},{"id":"a21I.ts","timestamp":1653310069454},{"id":"KWZu.ts","timestamp":1653310449513},{"id":"Hrmg.ts","source":"undoRedo.source","timestamp":1653310638947},{"id":"oAd9.ts","timestamp":1653392726169},{"id":"l2ne.ts","source":"Workspace Edit","timestamp":1653402445753},{"id":"oS9f.ts","timestamp":1653402509965},{"id":"gR04.ts","timestamp":1653402611585}]}